drf_pydantic_serializer/__init__.py
drf_pydantic_serializer/apps.py
drf_pydantic_serializer/field_extensions.py
drf_pydantic_serializer/fields.py
drf_pydantic_serializer/serializers.py
drf_pydantic_serializer-0.1.0.dist-info/METADATA
drf_pydantic_serializer-0.1.0.dist-info/WHEEL
drf_pydantic_serializer-0.1.0.dist-info/RECORD
