Metadata-Version: 2.4
Name: drf-pydantic-serializer
Version: 0.1.0
Summary: Add your description here
Requires-Python: >=3.12
Requires-Dist: djangorestframework>=3.16.1
Requires-Dist: pydantic>=2.11.9
